kabukit/__init__.py
kabukit/analysis/__init__.py
kabukit/analysis/indicators.py
kabukit/analysis/preprocess.py
kabukit/analysis/screener.py
kabukit/analysis/visualization/__init__.py
kabukit/analysis/visualization/market.py
kabukit/analysis/visualization/prices.py
kabukit/cli/__init__.py
kabukit/cli/app.py
kabukit/cli/auth.py
kabukit/cli/cache.py
kabukit/cli/get.py
kabukit/cli/utils.py
kabukit/domain/__init__.py
kabukit/domain/base.py
kabukit/domain/edinet/__init__.py
kabukit/domain/edinet/list.py
kabukit/domain/jquants/__init__.py
kabukit/domain/jquants/info.py
kabukit/domain/jquants/prices.py
kabukit/domain/jquants/statements.py
kabukit/domain/tdnet/__init__.py
kabukit/domain/tdnet/list.py
kabukit/py.typed
kabukit/sources/__init__.py
kabukit/sources/client.py
kabukit/sources/columns.py
kabukit/sources/datetime.py
kabukit/sources/edinet/__init__.py
kabukit/sources/edinet/client.py
kabukit/sources/edinet/columns.py
kabukit/sources/edinet/fetcher.py
kabukit/sources/edinet/parser.py
kabukit/sources/edinet/transform.py
kabukit/sources/jpx/__init__.py
kabukit/sources/jpx/client.py
kabukit/sources/jpx/fetcher.py
kabukit/sources/jpx/parser.py
kabukit/sources/jquants/__init__.py
kabukit/sources/jquants/client.py
kabukit/sources/jquants/columns.py
kabukit/sources/jquants/fetcher.py
kabukit/sources/jquants/transform/__init__.py
kabukit/sources/jquants/transform/calendar.py
kabukit/sources/jquants/transform/info.py
kabukit/sources/jquants/transform/prices.py
kabukit/sources/jquants/transform/statements.py
kabukit/sources/jquants/transform/topix.py
kabukit/sources/tdnet/__init__.py
kabukit/sources/tdnet/client.py
kabukit/sources/tdnet/columns.py
kabukit/sources/tdnet/fetcher.py
kabukit/sources/tdnet/parser.py
kabukit/sources/tdnet/transform.py
kabukit/sources/utils.py
kabukit/sources/yahoo/__init__.py
kabukit/sources/yahoo/client.py
kabukit/sources/yahoo/fetcher.py
kabukit/sources/yahoo/parser.py
kabukit/utils/__init__.py
kabukit/utils/cache.py
kabukit/utils/config.py
kabukit-0.18.0.dist-info/WHEEL
kabukit-0.18.0.dist-info/entry_points.txt
kabukit-0.18.0.dist-info/METADATA
kabukit-0.18.0.dist-info/RECORD
