Metadata-Version: 2.3
Name: kabukit
Version: 0.18.0
Summary: A Python toolkit for Japanese financial market data, supporting J-Quants and EDINET APIs.
Keywords: J-Quants,EDINET,financial data,stock market,investment,toolkit,finance,trading,data analysis,polars
Author: daizutabi
Author-email: daizutabi <daizutabi@gmail.com>
License: MIT License
Classifier: Development Status :: 4 - Beta
Classifier: Programming Language :: Python
Classifier: Programming Language :: Python :: 3 :: Only
Classifier: Programming Language :: Python :: 3.12
Classifier: Programming Language :: Python :: 3.13
Classifier: Programming Language :: Python :: 3.14
Classifier: License :: OSI Approved :: MIT License
Classifier: Operating System :: OS Independent
Classifier: Intended Audience :: Developers
Classifier: Intended Audience :: Financial and Insurance Industry
Classifier: Intended Audience :: Science/Research
Classifier: Topic :: Office/Business :: Financial
Classifier: Topic :: Software Development :: Libraries :: Python Modules
Classifier: Topic :: Scientific/Engineering :: Information Analysis
Classifier: Topic :: Utilities
Requires-Dist: async-typer>=0.1.0,<1.0
Requires-Dist: beautifulsoup4>=4.0
Requires-Dist: httpx>=0.28.0,<1.0
Requires-Dist: ixbrlparse>=0.11.1
Requires-Dist: lxml>=6.0
Requires-Dist: platformdirs>=4.0
Requires-Dist: polars>=1.32.3
Requires-Dist: pypdf>=6.1.3
Requires-Dist: rich>=12.0
Requires-Dist: tenacity>=9.0
Requires-Dist: toml>=0.10.2,<1.0
Requires-Dist: tqdm>=4.48
Requires-Dist: typer>=0.19.0,<1.0
Requires-Dist: tzdata ; sys_platform == 'win32'
Requires-Python: >=3.12
Project-URL: Changelog, https://github.com/daizutabi/kabukit/releases
Project-URL: Documentation, https://daizutabi.github.io/kabukit/
Project-URL: Homepage, https://daizutabi.github.io/kabukit/
Project-URL: Issues, https://github.com/daizutabi/kabukit/issues
Project-URL: Source, https://github.com/daizutabi/kabukit
